bousarout_de_toolkit/__init__.py
bousarout_de_toolkit/main.py
bousarout_de_toolkit/vm.py
bousarout_de_toolkit-0.1.0.dist-info/METADATA
bousarout_de_toolkit-0.1.0.dist-info/WHEEL
bousarout_de_toolkit-0.1.0.dist-info/entry_points.txt
bousarout_de_toolkit-0.1.0.dist-info/RECORD
