Metadata-Version: 2.1
Name: bousarout-de-toolkit
Version: 0.1.0
Summary: 
Author: BOUSAROUT
Author-email: mohamed.bousarout@lewagon-data-eng-vm-mbo3224.europe-west9-a.c.lewagon-412213.internal
Requires-Python: >=3.8,<4.0
Classifier: Programming Language :: Python :: 3
Classifier: Programming Language :: Python :: 3.8
Classifier: Programming Language :: Python :: 3.9
Classifier: Programming Language :: Python :: 3.10
Classifier: Programming Language :: Python :: 3.11
Classifier: Programming Language :: Python :: 3.12
Requires-Dist: click (>=8.1.7,<9.0.0)
